bandicoincurrency/__init__.py
bandicoincurrency/bandicoincurrency.py
bandicoincurrency-0.0.7.dist-info/METADATA
bandicoincurrency-0.0.7.dist-info/WHEEL
bandicoincurrency-0.0.7.dist-info/top_level.txt
bandicoincurrency-0.0.7.dist-info/RECORD
