Metadata-Version: 2.1
Name: bandicoincurrency
Version: 0.0.7
Summary: Bandicoin scratch project wrapper for external payments
Author: cbt1
Classifier: Programming Language :: Python :: 3
Classifier: License :: OSI Approved :: MIT License
Classifier: Operating System :: OS Independent
Requires-Python: >=3.6
